<?xml version="1.0" encoding="UTF-8"?>
<objects serializationModel="Studio.02.00.00">
	<object class="AudioFile" id="{4a8ecdb5-99a8-48ae-9ce4-30e3941c6e94}">
		<property name="assetPath">
			<value>remporte victoire j1.wav</value>
		</property>
		<property name="frequencyInKHz">
			<value>44.0999985</value>
		</property>
		<property name="channelCount">
			<value>2</value>
		</property>
		<property name="length">
			<value>3.6923129251700679</value>
		</property>
		<relationship name="masterAssetFolder">
			<destination>{e579ccfe-ed38-4b72-b609-9edebfefcf05}</destination>
		</relationship>
	</object>
</objects>
